nima/__init__.py
nima/__main__.py
nima/generat.py
nima/nima.py
nima/nima_types.py
nima/py.typed
nima/segmentation.py
nima/utils.py
nima-0.11.9.dist-info/METADATA
nima-0.11.9.dist-info/WHEEL
nima-0.11.9.dist-info/entry_points.txt
nima-0.11.9.dist-info/licenses/LICENSE.txt
nima-0.11.9.dist-info/RECORD
