Metadata-Version: 2.4
Name: nima
Version: 0.11.9
Summary: Numerical IMage Analyses.
Project-URL: Bug Tracker, https://github.com/darosio/nima/issues
Project-URL: Changelog, https://github.com/darosio/nima/blob/main/CHANGELOG.md
Project-URL: Documentation, https://nima.readthedocs.io
Project-URL: Github releases, https://github.com/darosio/nima/releases
Project-URL: Homepage, https://github.com/darosio/nima
Project-URL: repository, https://github.com/darosio/nima/
Author-email: daniele arosio <daniele.arosio@cnr.it>
License-Expression: BSD-3-Clause
License-File: LICENSE.txt
Keywords: ClopHensor,chloride,image analysis,pH,ratio imaging
Classifier: Development Status :: 2 - Pre-Alpha
Classifier: Environment :: Console
Classifier: Intended Audience :: Science/Research
Classifier: Operating System :: OS Independent
Classifier: Programming Language :: Python :: 3
Classifier: Programming Language :: Python :: 3.11
Classifier: Programming Language :: Python :: 3.12
Classifier: Programming Language :: Python :: 3.13
Classifier: Programming Language :: Unix Shell
Classifier: Topic :: Scientific/Engineering
Requires-Python: >=3.11
Requires-Dist: bioio-tifffile>=1.3.0
Requires-Dist: click>=8.3.0
Requires-Dist: dask[distributed]>=2025.9.1
Requires-Dist: matplotlib>=3.10.6
Requires-Dist: numpy>=2.3.3
Requires-Dist: pandas>=2.3.2
Requires-Dist: pims>=0.7
Requires-Dist: pyarrow>=21.0.0
Requires-Dist: s3fs>=2025.9.0
Requires-Dist: scikit-image>=0.25.2
Requires-Dist: scipy>=1.16.2
Requires-Dist: sigfig>=1.3.19
Requires-Dist: tifffile>=2025.9.9
Requires-Dist: xmltodict>=1.0.2
